boututils/View3D.py
boututils/__init__.py
boututils/_version.py
boututils/analyse_equil_2.py
boututils/anim.py
boututils/ask.py
boututils/boutarray.py
boututils/boutgrid.py
boututils/boutwarnings.py
boututils/bunch.py
boututils/calculus.py
boututils/check_scaling.py
boututils/closest_line.py
boututils/crosslines.py
boututils/datafile.py
boututils/efit_analyzer.py
boututils/fft_deriv.py
boututils/fft_integrate.py
boututils/file_import.py
boututils/geqdsk.py
boututils/idl_tabulate.py
boututils/int_func.py
boututils/linear_regression.py
boututils/local_min_max.py
boututils/mode_structure.py
boututils/moment_xyzt.py
boututils/options.py
boututils/plotdata.py
boututils/plotpolslice.py
boututils/radial_grid.py
boututils/read_geqdsk.py
boututils/run_wrapper.py
boututils/showdata.py
boututils/spectrogram.py
boututils/surface_average.py
boututils/volume_integral.py
boututils/watch.py
boututils/tests/__init__.py
boututils/tests/test_import.py
boututils-0.2.1.dist-info/LICENSE
boututils-0.2.1.dist-info/METADATA
boututils-0.2.1.dist-info/WHEEL
boututils-0.2.1.dist-info/top_level.txt
boututils-0.2.1.dist-info/RECORD
