Metadata-Version: 2.1
Name: boututils
Version: 0.2.1
Summary: Python utilities for BOUT++
Author: Ben Dudson, BOUT++ team
License: GNU LESSER GENERAL PUBLIC LICENSE
Project-URL: Tracker, https://github.com/boutproject/boututils/issues/
Project-URL: Documentation, https://bout-dev.readthedocs.io/en/latest/
Project-URL: Source, https://github.com/boutproject/boututils/
Keywords: bout++,bout,plasma,physics,data-extraction,data-analysis,data-visualization
Classifier: Programming Language :: Python :: 3
Classifier: Intended Audience :: Science/Research
Classifier: License :: OSI Approved :: GNU Lesser General Public License v3 or later (LGPLv3+)
Classifier: Operating System :: OS Independent
Classifier: Topic :: Software Development :: Libraries :: Python Modules
Requires-Python: >=3.8
License-File: LICENSE
Requires-Dist: numpy >=1.22.0
Requires-Dist: matplotlib >=3.2.1
Requires-Dist: scipy >=1.4.1
Requires-Dist: netCDF4
Provides-Extra: docs
Requires-Dist: sphinx <5,>=3.4 ; extra == 'docs'
Provides-Extra: tests
Requires-Dist: pytest ; extra == 'tests'
Requires-Dist: pytest-cov ; extra == 'tests'
